apyk/__init__.py
apyk/functions.py
apyk/icon.ico
apyk/test.global.py
apyk/test.thread.py
apyk/ui_backupscreen.py
apyk/ui_main.py
apyk/win_main.py
APyK-0.0.2.dist-info/LICENSE
APyK-0.0.2.dist-info/METADATA
APyK-0.0.2.dist-info/WHEEL
APyK-0.0.2.dist-info/entry_points.txt
APyK-0.0.2.dist-info/top_level.txt
APyK-0.0.2.dist-info/RECORD
