Metadata-Version: 2.1
Name: APyK
Version: 0.0.2
Summary: APyK is a program with which you will be able to backup your applications from your computer.
Home-page: https://github.com/Jalkhov/apyk
Author: Pedro Torcatt
Author-email: pedrotorcattsoto@gmail.com
License: MIT
Keywords: adb android apk backup apps
Platform: UNKNOWN
Classifier: Topic :: Utilities
Classifier: Environment :: Win32 (MS Windows)
Classifier: Topic :: System :: Archiving :: Backup
Classifier: Programming Language :: Python :: 3
Classifier: License :: OSI Approved :: MIT License
Classifier: Operating System :: Microsoft :: Windows
Classifier: Development Status :: 5 - Production/Stable
Requires-Python: >=3.5
Requires-Dist: PyQt5
Requires-Dist: google-play-scraper
